Workbook

Sheet README
A1: GTM Role Compensation Program — v4
A2: Role-based, person-agnostic. Effective [date]. Supersedes v3 (person-specific model).
A4: WHAT THIS IS
A5: A compensation program for two part-time contractor GTM roles. It is designed around the company's needs,
A6: not any individual. Anyone hired into a role is paid by the same rules. One person may hold both roles;
A7: comp stacks, hours do not double-count.
A9: DESIGN PRINCIPLES
A10: 1. Pay for outcomes at market-fair rates: qualified meetings held and cash collected, not activity volume.
A11: 2. Commissions are on COLLECTED cash only. Max two payouts per deal. No open-ended trailing payments.
A12: 3. Fairness floor: base + realistic variable should clear ~$15/hr for committed hours (see Scenarios hourly check).
A13: 4. ICP guardrail: only meetings/deals in approved lanes count. New lanes need written approval BEFORE list-building.
A14: 5. When a role ends: earned amounts are paid; the deal ledger closes 90 days after the end date.
... A32: • Avg MRR default of $39 reflects current live price points ($29–39 single-seat; $20 founding-nonprofit bridge).

Sheet Roles
A1: Role Definitions
A3: ROLE 1 — OUTBOUND SDR (part-time contractor) | B3: ROLE 2 — CONTENT & COMMUNITY (part-time contractor)
A4: Mission: book qualified meetings with approved-ICP prospects. | B4: Mission: ship approved content that supports the GTM motion.
A5: Committed floor: 10 hrs/week (base covers this). Typical: 15–20. | B5: No committed hours — paid per shipped, approved piece.
A6: Owns: | B6: Owns:
A7: • List building in approved lanes only | B7: • Survey-led posts (public survey → findings post)
A8: • Personalized outreach — every send individually researched; | B8: • Testimonial cuts from customer video
A9: first 2 weeks of sends reviewed before sending | B9: • Case studies / long-form (with founder input)
A10: • Follow-up sequences (touches 2–4) — most replies live here | B10: • Event recaps and community posts
A11: • Booking + meeting prep; same-day notes to founder | B11: Does NOT own:
A12: • Daily end-of-day tracker (see Daily_Tracker) | B12: • Outreach or DMs at scale
A13: Does NOT own: | B13: • Influencer / partnership deals — written approval first
A14: • Closing (founder closes), pricing, discounts | B14: • Publishing without approval (every piece is gated)
... A17: Compensation: SDR_Comp tab. | B17: Compensation: Content_Comp tab.
A20: One person may hold both roles. Comp stacks; committed hours are counted once. If the split ever feels unfair, fix the rates on the comp tabs — not by side deals.

Sheet SDR_Comp
A1: Outbound SDR — Compensation Rules
A2: Yellow cells are program inputs. Calculator and Scenarios reference these.
A4: BASE
A5: Monthly base ($) | B5: 650 | C5: Guaranteed. Covers the 10 hr/week committed floor.
A6: Committed hours/week (floor) | B6: 10 | C6: Below this two weeks running → base pro-rates.
A7: Implied floor rate ($/hr) | B7: =B5/(B6*52/12) | C7: Fairness check: keep ≥ ~$15/hr.
A9: MEETING PAYOUT
A10: Per qualified meeting held ($) | B10: 50 | C10: Held = happened. Booked-only pays nothing.
A12: Qualified meeting = ALL of the following:
A13: 1. Prospect fits an approved lane (see ICP guardrail below)
A14: 2. Meeting actually occurs — no-shows do NOT count
A15: 3. Prospect is net-new: not already in pipeline, not an existing customer
A16: 4. At least 20 minutes of real discussion
A17: 5. Founder visibility: on the invite, or notes shared same-day
A19: CLOSE INCENTIVES — collected cash only
A20: Close bounty (× first month collected) | B20: 2 | C20: Paid after the customer's first payment clears. On annual prepay: bounty on the monthly-equivalent.
A21: Retention true-up (% of Y1 value = 12 × MRR) | B21: 0.1 | C21: Paid ONCE, only if the customer is still active on day 90.
A22: Max payouts per deal: two (bounty + true-up). No trailing commissions.
A23: Applies to deals the SDR sourced (their outreach/booking). Founder-sourced deals: no commission — covered by base.
A25: ICP GUARDRAIL
A26: Approved lanes (current): 1) Consultants / fractional operators · 2) Member orgs (nonprofits, accelerators, associations).
A27: Meetings and deals outside approved lanes pay $0. New lanes require written approval BEFORE any list-building.
A29: MARKET REFERENCE (fairness rationale — stated assumptions, set by Rick)
A30: • Typical SDR pay mix: 60/40 to 70/30 base/variable. This plan lands ~65/35 at target.
A31: • Meeting-held spiffs commonly $25–$100 for SMB deal sizes.
A32: • Sourced-close incentives commonly 5–10% of first-year value; this plan's bounty + true-up ≈ 10–27% of Y1
A33: cash at current small deal sizes — deliberately above standard while deals are small, so wins stay meaningful.
A35: PAYMENT TIMING
A36: Base | C36: 1st of month
A37: Meeting payouts | C37: With base, monthly, per tracker + calendar record
A38: Close bounty | C38: First payroll after customer payment clears
A39: Retention true-up | C39: First payroll after day 90 with customer active
A40: Role ends | C40: Earned amounts paid out; deal ledger closes 90 days after end date

Sheet Content_Comp
A1: Content & Community — Compensation Rules
A2: Yellow cells are program inputs. Paid per shipped, approved piece.
A4: RATE CARD (per shipped + approved piece)
A5: Social post (researched, written, edited) | B5: 35 | C5: e.g. survey-findings post, community post
A6: Short video clip / edit | B6: 75 | C6: Product clips, event cuts
A7: Testimonial cut (customer video) | B7: 100 | C7: Sourced + permissioned + edited
A8: Case study / long-form | B8: 150 | C8: With founder input on claims
A10: Optional cadence retainer ($/mo) | B10: 200 | C10: Only with a committed 2-pieces/week cadence. Otherwise pure per-piece.
A11: Monthly cap (pieces) | B11: 8 | C11: Above cap needs pre-approval — protects review bandwidth.
A13: QUALITY GATE — a piece pays only if ALL are true:
A14: 1. The person researched, drafted, and edited it. Raw AI output does not count.
A15: 2. Founder approved it before/at publication (24–48h review turnaround owed in return).
A16: 3. It actually shipped — published or delivered to a prospect/customer.
A17: 4. Quality bar: coherent narrative, factually correct, has a point of view.
A19: MARKET REFERENCE (stated assumptions, set by Rick)
A20: • Junior freelance per-piece rates commonly $25–$200 by format and length; this card sits at the junior end,
A21: reflecting heavy founder review. Raise rates as review need drops.

Sheet Calculator
A1: Monthly Earnings Calculator
A2: Edit the yellow activity cells. Earnings compute from the comp tabs.
A4: SDR ROLE — activity this month
A5: Qualified meetings held | B5: 4 | C5: Meets all 5 criteria on SDR_Comp
A6: Sourced deals closed (first payment collected) | B6: 1
A7: Avg MRR of those deals ($) | B7: 39 | C7: $29–39 single-seat; $20 founding bridge
A8: Prior deals passing day-90 retention this month | B8: 0
A10: SDR EARNINGS
A11: Base | B11: =SDR_Comp!B5
A12: Meeting payouts | B12: =B5*SDR_Comp!B10
A13: Close bounties | B13: =B6*SDR_Comp!B20*B7
A14: Retention true-ups | B14: =B8*SDR_Comp!B21*12*B7
A15: SDR TOTAL | B15: =SUM(B11:B14)
A17: CONTENT ROLE — pieces shipped this month
A18: Social posts | B18: 2
A19: Short video clips | B19: 1
A20: Testimonial cuts | B20: 0
A21: Case studies / long-form | B21: 0
A22: Cadence retainer active? (1 = yes, 0 = no) | B22: 0
A24: CONTENT TOTAL | B24: =B18*Content_Comp!B5+B19*Content_Comp!B6+B20*Content_Comp!B7+B21*Content_Comp!B8+B22*Content_Comp!B10
A26: COMBINED (one person, both roles) | B26: =B15+B24

Sheet Scenarios
A1: Planning Scenarios
A2: Program inputs come from the comp tabs; activity assumptions below are editable.
A4: SDR ROLE | B4: FLOOR | C4: TARGET | D4: STRETCH
A5: Qualified meetings/month | B5: 2 | C5: 6 | D5: 10
A6: Sourced closes/month | B6: 0 | C6: 1 | D6: 2
A7: Avg MRR ($) | B7: 39 | C7: 39 | D7: 39
A8: Deals passing day-90/month | B8: 0 | C8: 0 | D8: 1
A9: Hours/week worked | B9: 10 | C9: 15 | D9: 20
A11: Base | B11: =SDR_Comp!$B$5 | C11: =SDR_Comp!$B$5 | D11: =SDR_Comp!$B$5
A12: Meeting payouts | B12: =B5*SDR_Comp!$B$10 | C12: =C5*SDR_Comp!$B$10 | D12: =D5*SDR_Comp!$B$10
A13: Close bounties | B13: =B6*SDR_Comp!$B$20*B7 | C13: =C6*SDR_Comp!$B$20*C7 | D13: =D6*SDR_Comp!$B$20*D7
A14: Retention true-ups | B14: =B8*SDR_Comp!$B$21*12*B7 | C14: =C8*SDR_Comp!$B$21*12*C7 | D14: =D8*SDR_Comp!$B$21*12*D7
A15: TOTAL / MONTH | B15: =SUM(B11:B14) | C15: =SUM(C11:C14) | D15: =SUM(D11:D14) | E15: Fairness check: hourly equivalent should stay ≥ ~$15/hr at every level.
A16: Hourly equivalent ($/hr) | B16: =B15/(B9*52/12) | C16: =C15/(C9*52/12) | D16: =D15/(D9*52/12)
A18: What each level looks like
A19: FLOOR | E19: Minimum commitment met, little conversion yet. Base carries it.
A20: TARGET | E20: Working funnel: ~1.5 meetings/wk, one small close/month. Realistic by week 4–6 of consistent, personalized outreach.
A21: STRETCH | E21: Strong funnel + retention landing. Approaching prior $1,200 flat — now earned, not granted.
A23: CONTENT ROLE | B23: FLOOR | C23: TARGET | D23: STRETCH
A24: Social posts | B24: 2 | C24: 3 | D24: 4
A25: Short video clips | B25: 0 | C25: 1 | D25: 2
A26: Testimonial cuts | B26: 0 | C26: 1 | D26: 1
A27: Case studies / long-form | B27: 0 | C27: 0 | D27: 1
A28: Cadence retainer (1/0) | B28: 0 | C28: 1 | D28: 1
A29: TOTAL / MONTH | B29: =B24*Content_Comp!$B$5+B25*Content_Comp!$B$6+B26*Content_Comp!$B$7+B27*Content_Comp!$B$8+B28*Content_Comp!$B$10 | C29: =C24*Content_Comp!$B$5+C25*Content_Comp!$B$6+C26*Content_Comp!$B$7+C27*Content_Comp!$B$8+C28*Content_Comp!$B$10 | D29: =D24*Content_Comp!$B$5+D25*Content_Comp!$B$6+D26*Content_Comp!$B$7+D27*Content_Comp!$B$8+D28*Content_Comp!$B$10

Sheet Daily_Tracker
A1: Daily End-of-Day Tracker (SDR role)
A2: Submitted by 6pm every working day. Copy a blank row per day; the EXAMPLE row shows expected format.
A4: Date | B4: Hours | C4: Meetings held | D4: Meetings booked | E4: Personalized emails sent | F4: Follow-ups sent | G4: Blockers | H4: Notes / wins
A5: EXAMPLE — Mon 8/17 | B5: 4 | C5: 1 | D5: 1 | E5: 6 | F5: 9 | G5: None | H5: Booked Kateri intro call for Thu
A7: Rules
A8: 1. By 6pm local, every working day. Illness excepted; silence is not.
A9: 2. Zeros are fine and honest. Pretending to be busy is not.
A10: 3. Late 3× in a month → that month's base pro-rates.
A11: 4. 'Personalized emails' means individually researched. Batch/mail-merge sends belong in no column — they don't count.
A12: 5. Blockers = things the founder can unblock. Recurring blockers are a management signal, not a complaint.
A13: 6. Friday: one short written summary compiling the week (activity, outcomes, blockers) before the weekly sync.
A15: What the founder reviews weekly
A16: • Meetings held vs booked (conversion) · replies per 10 personalized sends (quality) · days below expectation (pattern)
A17: • Whether the founder was the blocker (review turnarounds owed: same-day for sends, 24–48h for content)
